[
  {
    "name": "Advanced",
    "description": "You have completed 5 tasks!",
    "numberOfTasksRequired": 5
  },
  {
    "name": "Expert",
    "description": "You have completed 10 tasks!",
    "numberOfTasksRequired": 10
  },
  {
    "name": "Starter",
    "description": "You have completed your first task!",
    "numberOfTasksRequired": 1
  },
  {
    "name": "Master",
    "description": "You have completed 20 tasks!",
    "numberOfTasksRequired": 20
  },
  {
    "name": "Legendary",
    "description": "You have completed 25 tasks!",
    "numberOfTasksRequired": 25
  }
]